pepe/__init__.py
pepe/__main__.py
pepe/model_selecter.py
pepe/parse_arguments.py
pepe/utils.py
pepe/embedders/__init__.py
pepe/embedders/base_embedder.py
pepe/embedders/custom_embedder.py
pepe/embedders/esm_embedder.py
pepe/embedders/huggingface_embedder.py
pepe_cli-1.0.3.dist-info/licenses/LICENSE
tests/__init__.py
tests/test_run.py
pepe_cli-1.0.3.dist-info/METADATA
pepe_cli-1.0.3.dist-info/WHEEL
pepe_cli-1.0.3.dist-info/entry_points.txt
pepe_cli-1.0.3.dist-info/top_level.txt
pepe_cli-1.0.3.dist-info/RECORD
