Metadata-Version: 2.4
Name: pepe-cli
Version: 1.0.3
Summary: Pipeline for Easy Protein Embedding - Extract embeddings and attention matrices from protein sequences
Home-page: https://github.com/csi-greifflab/pepe-cli
Author: Jahn Zhong
Author-email: Jahn Zhong <jahn.zhong@medisin.uio.no>
License: MIT
Project-URL: Homepage, https://github.com/csi-greifflab/pepe-cli
Project-URL: Bug Reports, https://github.com/csi-greifflab/pepe-cli/issues
Project-URL: Source, https://github.com/csi-greifflab/pepe-cli
Project-URL: Documentation, https://github.com/csi-greifflab/pepe-cli#readme
Keywords: protein,embeddings,bioinformatics,machine-learning,nlp,transformers
Classifier: Development Status :: 3 - Alpha
Classifier: Intended Audience :: Science/Research
Classifier: License :: OSI Approved :: GNU Affero General Public License v3
Classifier: Operating System :: OS Independent
Classifier: Programming Language :: Python :: 3
Classifier: Programming Language :: Python :: 3.8
Classifier: Programming Language :: Python :: 3.9
Classifier: Programming Language :: Python :: 3.10
Classifier: Programming Language :: Python :: 3.11
Classifier: Topic :: Scientific/Engineering :: Bio-Informatics
Classifier: Topic :: Scientific/Engineering :: Artificial Intelligence
Requires-Python: >=3.8
License-File: LICENSE
Requires-Dist: torch>=1.9.0
Requires-Dist: transformers>=4.20.0
Requires-Dist: fair-esm
Requires-Dist: sentencepiece
Requires-Dist: numpy
Requires-Dist: protobuf
Requires-Dist: rjieba
Requires-Dist: alive_progress
Dynamic: author
Dynamic: home-page
Dynamic: license-file
Dynamic: requires-python
